MANIFEST.in
README.rst
setup.py
cltwit/__init__.py
cltwit/cltwitdb.py
cltwit/cltwitreport.py
cltwit/main.py
cltwit/sqlite2csv.py
cltwit/utils.py
cltwit.egg-info/PKG-INFO
cltwit.egg-info/SOURCES.txt
cltwit.egg-info/dependency_links.txt
cltwit.egg-info/entry_points.txt
cltwit.egg-info/namespace_packages.txt
cltwit.egg-info/not-zip-safe
cltwit.egg-info/requires.txt
cltwit.egg-info/top_level.txt
cltwit/locale/en/LC_MESSAGES/cltwit.mo
cltwit/locale/fr/LC_MESSAGES/cltwit.mo