Metadata-Version: 1.1
Name: cltwit
Version: 0.6
Summary: 'Command line Twitter utility'
Home-page: http://forge.projet-libre.org/projects/cltwit/wiki
Author: Jérôme Launay
Author-email: jerome@projet-libre.org
License: WTFPL
Keywords: 'twitter command-line follow unfollo export tweet'
Platform: UNKNOWN
Classifier: Programming Language :: Python
Classifier: Natural Language :: French
Classifier: Operating System :: OS Independent
Classifier: Programming Language :: Python :: 2.7
Classifier: Topic :: Terminals
Classifier: Topic :: Utilities
